{
  "schemaVersion": 1,
  "id": "clientsidetesting",
  "version": "1.1.11",
  "name": "Clientside Testing",
  "description": "A mod implementing some general use client side features.",
  "authors": [
    "Logan Schaaf"
  ],
  "contact": {
    "sources": "https://github.com/bookwormpi/ClientMods"
  },
  "license": "MIT",
  "environment": "client",
  "entrypoints": {
    "main": [
      "org.bookwormpi.clientsidetesting.client.ClientsidetestingClient"
    ]
  },
  "depends": {
    "fabricloader": ">=0.14.0",
    "fabric": "*",
    "minecraft": ">=1.21.0 <1.22.0"
  }
}